atcoder_helper/__init__.py
atcoder_helper/__main__.py
atcoder_helper/_version.py
atcoder_helper/program_executor.py
atcoder_helper/default_configs/default_config.yaml
atcoder_helper/default_configs/templates/cpp-clang/main.cpp
atcoder_helper/default_configs/templates/cpp-gcc/main.cpp
atcoder_helper/default_configs/templates/python/task.py
atcoder_helper/default_configs/templates/python-pypy3/task.py
atcoder_helper/models/__init__.py
atcoder_helper/models/atcoder_helper_config.py
atcoder_helper/models/atcoder_task_config.py
atcoder_helper/models/atcoder_test_case.py
atcoder_helper/repositories/__init__.py
atcoder_helper/repositories/atcoder_helper_config_repo.py
atcoder_helper/repositories/atcoder_logged_in_session_repo.py
atcoder_helper/repositories/atcoder_test_case_repo.py
atcoder_helper/repositories/errors.py
atcoder_helper/repositories/local_test_case_repo.py
atcoder_helper/repositories/logged_in_session_repo.py
atcoder_helper/repositories/login_status_repo.py
atcoder_helper/repositories/task_config_repo.py
atcoder_helper/repositories/utils.py
atcoder_helper/scripts/__init__.py
atcoder_helper/scripts/executor.py
atcoder_helper/scripts/main.py
atcoder_helper/scripts/parser.py
atcoder_helper/services/__init__.py
atcoder_helper/services/atcoder_helper_config.py
atcoder_helper/services/auth.py
atcoder_helper/services/errors.py
atcoder_helper/services/execute_test.py
atcoder_helper/services/fetch_task.py
atcoder_helper/services/init_task.py
atcoder_helper/services/util.py
tests/__init__.py
tests/models/__init__.py
tests/models/test_atcoder_helper_config.py
tests/models/test_task_config.py
tests/models/test_test_cases.py
tests/repositories/__init__.py
tests/repositories/test_atcoder_helper_config_repo.py
tests/repositories/test_atcoder_logged_in_session_repo.py
tests/repositories/test_atcoder_test_case_repo.py
tests/repositories/test_local_test_case_repo.py
tests/scripts/__init__.py
tests/scripts/test_executor.py
atcoder_helper-0.1.11.dist-info/LICENSE
atcoder_helper-0.1.11.dist-info/METADATA
atcoder_helper-0.1.11.dist-info/WHEEL
atcoder_helper-0.1.11.dist-info/entry_points.txt
atcoder_helper-0.1.11.dist-info/top_level.txt
atcoder_helper-0.1.11.dist-info/RECORD
