Metadata-Version: 2.1
Name: atcoder-helper
Version: 0.1.11
Summary: automation cli tools for AtCoder
Home-page: https://github.com/yuchiki/atcoder_helper
Download-URL: https://github.com/yuchiki/atcoder_helper
Author: yuchiki
Author-email: yuki.imai77@gmail.com
Maintainer: yuchiki
Maintainer-email: yuki.imai77@gmail.com
License: MIT LICENSE
Classifier: Programming Language :: Python :: 3
Classifier: License :: OSI Approved :: MIT License
Classifier: Operating System :: OS Independent
Requires-Python: >=3.10
License-File: LICENSE
Requires-Dist: colorama
Requires-Dist: beautifulsoup4
Requires-Dist: requests
Requires-Dist: pyyaml
Requires-Dist: pydantic
